pynd/__init__.py
pynd/__main__.py
pynd/astutils.py
pynd/cli.py
pynd/filters.py
pynd/pattern.py
pynd/search.py
pynd/_tests/__init__.py
pynd/_tests/test_astutils.py
pynd/_tests/test_cli.py
pynd/_tests/test_code.txt
pynd/_tests/test_filters.py
pynd/_tests/test_main.py
pynd/_tests/test_search.py
pynd-0.3.6.dist-info/DESCRIPTION.rst
pynd-0.3.6.dist-info/METADATA
pynd-0.3.6.dist-info/RECORD
pynd-0.3.6.dist-info/WHEEL
pynd-0.3.6.dist-info/entry_points.txt
pynd-0.3.6.dist-info/metadata.json
pynd-0.3.6.dist-info/pbr.json
pynd-0.3.6.dist-info/top_level.txt
