Metadata-Version: 2.0
Name: pynd
Version: 0.3.6
Summary: Searching in Python
Home-page: https://github.com/d0ugal/pynd
Author: Dougal Matthews
Author-email: dougal@dougalmatthews.com
License: Apache License, Version 2.0
Keywords: ast
Requires-Dist: pbr (>=1.8)
